halo_third_party_sdk_events/__init__.py
halo_third_party_sdk_events/__version__.py
halo_third_party_sdk_events/event_verification_handler.py
halo_third_party_sdk_events/py.typed
halo_third_party_sdk_events/serialize.py
halo_third_party_sdk_events/verifier.py
halo_third_party_sdk_events/verifier_constants.py
halo_third_party_sdk_events-2.0.0.dist-info/LICENSE
halo_third_party_sdk_events-2.0.0.dist-info/METADATA
halo_third_party_sdk_events-2.0.0.dist-info/WHEEL
halo_third_party_sdk_events-2.0.0.dist-info/top_level.txt
halo_third_party_sdk_events-2.0.0.dist-info/RECORD
