Metadata-Version: 2.1
Name: halo-third-party-sdk-events
Version: 2.0.0
Summary: The Halo Third Party SDK Events package provides support for verifying the authenticity of events.
Home-page: https://github.com/amzn/halo-third-party-sdk-for-python
Author: Amazon Halo
Author-email: healthtech-partner-engineering-support@amazon.com
License: Apache 2.0
Keywords: Halo SDK,Amazon Halo
Classifier: Development Status :: 5 - Production/Stable
Classifier: Intended Audience :: Developers
Classifier: Natural Language :: English
Classifier: License :: OSI Approved :: Apache Software License
Classifier: Programming Language :: Python
Classifier: Programming Language :: Python :: 3
Classifier: Programming Language :: Python :: 3.6
Classifier: Programming Language :: Python :: 3.7
Requires-Python: !=3.0.*, !=3.1.*, !=3.2.*, !=3.3.*, !=3.4.*, !=3.5.*
License-File: LICENSE
Requires-Dist: halo-third-party-sdk-model (>=1.0.0)
Requires-Dist: cryptography (>=3.2)
Requires-Dist: certvalidator (>=0.11.1)
Requires-Dist: freezegun (>=0.3.15)
